Metadata-Version: 2.1
Name: top-hat
Version: 0.0.2
Summary: Recommendation system in TensorFlow
Home-page: https://github.com/gilt/tophat
Author: GILT-cerebro (Jason Tam)
Author-email: cerebro-dev@gilt.com (jtam@gilt.com)
License: MIT
Platform: UNKNOWN
Classifier: Development Status :: 3 - Alpha
Classifier: License :: OSI Approved :: MIT License
Classifier: Programming Language :: Python
Classifier: Programming Language :: Python :: 3
Classifier: Programming Language :: Python :: 3.6
Classifier: Programming Language :: Python :: 3 :: Only
Classifier: Topic :: Scientific/Engineering :: Artificial Intelligence
Requires-Python: >=3.6.0
Provides-Extra: tf
Provides-Extra: tf_gpu
Requires-Dist: pandas
Requires-Dist: numpy
Requires-Dist: scipy
Requires-Dist: tqdm
Provides-Extra: tf
Requires-Dist: tensorflow (>=1.9.0); extra == 'tf'
Provides-Extra: tf_gpu
Requires-Dist: tensorflow-gpu (>=1.9.0); extra == 'tf_gpu'
